microboxlabs_auth_manager/__init__.py
microboxlabs_auth_manager/auth_token.py
microboxlabs_auth_manager-0.1.2.dist-info/WHEEL
microboxlabs_auth_manager-0.1.2.dist-info/METADATA
microboxlabs_auth_manager-0.1.2.dist-info/RECORD
