Metadata-Version: 2.1
Name: microboxlabs-auth-manager
Version: 0.1.2
Summary: 
Author: Michel David
Author-email: mdavid.cu@gmail.com
Requires-Python: >=3.9,<4.0
Classifier: Programming Language :: Python :: 3
Classifier: Programming Language :: Python :: 3.9
Classifier: Programming Language :: Python :: 3.10
Classifier: Programming Language :: Python :: 3.11
Requires-Dist: pyjwt (>=2.8.0,<3.0.0)
Requires-Dist: requests (>=2.31.0,<3.0.0)
